{
  "project_info": {
    "project_number": "222212240039",
    "project_id": "fintracker-1a6c3",
    "storage_bucket": "fintracker-1a6c3.appspot.com"
  },
  "client": [
    {
      "client_info": {
        "mobilesdk_app_id": "1:222212240039:android:d0df56ffa4e5bbbc802182",
        "android_client_info": {
          "package_name": "com.example.myapplication"
        }
      },
      "oauth_client": [],
      "api_key": [
        {
          "current_key": "AIzaSyCwozOSPGw1TD5MyzWkoiNWNFBAN7xdk-Q"
        }
      ],
      "services": {
        "appinvite_service": {
          "other_platform_oauth_client": []
        }
      }
    }
  ],
  "configuration_version": "1"
}